pynoma/DataManager.py
pynoma/Logger.py
pynoma/Queries.py
pynoma/Search.py
pynoma/__init__.py
pynoma/helper.py
Pynoma-0.2.1.dist-info/LICENSE
Pynoma-0.2.1.dist-info/METADATA
Pynoma-0.2.1.dist-info/WHEEL
Pynoma-0.2.1.dist-info/top_level.txt
Pynoma-0.2.1.dist-info/RECORD
